{
  "type": "minecraft:crafting_shaped",
  "category": "misc",
  "pattern": [
    "SWG",
    "TDG",
    "GGG"
  ],
  "key": {
    "S": {
      "item": "minecraft:nether_wart"
    },
    "W": {
      "item": "minecraft:water_bucket"
    },
    "G": {
      "item": "minecraft:glass"
    },
    "T": [
      {
        "item": "minecraft:torch"
      },
      {
        "item": "minecraft:glowstone"
      }
    ],
    "D": {
      "item": "minecraft:soul_sand"
    }
  },
  "result": {
    "id": "travelersgarden:nether_wart_farm",
    "count": 1
  },
  "replacements": {
    "minecraft:water_bucket": "minecraft:bucket"
  }
}
